{"farm":{"crops":[],"soil":[{"wetness":0,"tilled":false,"x":-4,"y":0},{"wetness":0,"tilled":false,"x":-3,"y":0},{"wetness":0,"tilled":false,"x":-2,"y":0},{"wetness":0,"tilled":false,"x":-1,"y":0},{"wetness":0,"tilled":false,"x":0,"y":0},{"wetness":0,"tilled":false,"x":1,"y":0},{"wetness":0,"tilled":false,"x":2,"y":0},{"wetness":0,"tilled":false,"x":3,"y":0},{"wetness":0,"tilled":false,"x":4,"y":0},{"wetness":0,"tilled":false,"x":-4,"y":2},{"wetness":0,"tilled":false,"x":-3,"y":2},{"wetness":0,"tilled":false,"x":-2,"y":2},{"wetness":0,"tilled":false,"x":-1,"y":2},{"wetness":0,"tilled":false,"x":0,"y":2},{"wetness":0,"tilled":false,"x":1,"y":2},{"wetness":0,"tilled":false,"x":2,"y":2},{"wetness":0,"tilled":false,"x":3,"y":2},{"wetness":0,"tilled":false,"x":4,"y":2}]},"player":{"tool":"shovel","balance":50,"inventory":[{"id":"tool:shovel","qty":1,"stackable":false},{"id":"tool:watering","qty":1,"stackable":false},{"id":"seed:corn","qty":5,"stackable":true},{"id":"seed:wheat","qty":3,"stackable":true}],"capacity":40},"version":1}